mailinglogger/__init__.py
mailinglogger/common.py
mailinglogger/flood_template.txt
mailinglogger/mailinglogger.py
mailinglogger/summarisinglogger.py
mailinglogger/version.txt
mailinglogger/tests/__init__.py
mailinglogger/tests/shared.py
mailinglogger/tests/test_htmlfilter.py
mailinglogger/tests/test_mailinglogger.py
mailinglogger/tests/test_summarisinglogger.py
mailinglogger-6.0.0.dist-info/METADATA
mailinglogger-6.0.0.dist-info/WHEEL
mailinglogger-6.0.0.dist-info/top_level.txt
mailinglogger-6.0.0.dist-info/RECORD
