Metadata-Version: 2.1
Name: mailinglogger
Version: 6.0.0
Summary: Enhanced emailing handlers for the python logging package.
Home-page: https://github.com/Simplistix/mailinglogger
Author: Chris Withers
Author-email: chris@simplistix.co.uk
License: MIT
Keywords: logging email
Platform: UNKNOWN
Classifier: Development Status :: 6 - Mature
Classifier: Intended Audience :: Developers
Classifier: Intended Audience :: System Administrators
Classifier: License :: OSI Approved :: MIT License
Classifier: Topic :: Communications :: Email
Classifier: Topic :: Software Development :: Libraries :: Python Modules
Classifier: Topic :: System :: Logging
Classifier: Programming Language :: Python :: 3
Classifier: Programming Language :: Python :: 3.7
Classifier: Programming Language :: Python :: 3.8
Classifier: Programming Language :: Python :: 3.9
Classifier: Programming Language :: Python :: 3.10
Requires-Python: >=3.7
Provides-Extra: build
Requires-Dist: sphinx ; extra == 'build'
Requires-Dist: setuptools-git ; extra == 'build'
Requires-Dist: wheel ; extra == 'build'
Requires-Dist: twine ; extra == 'build'
Requires-Dist: sphinx-rtd-theme ; extra == 'build'
Provides-Extra: test
Requires-Dist: pytest ; extra == 'test'
Requires-Dist: pytest-cov ; extra == 'test'
Requires-Dist: sybil ; extra == 'test'
Requires-Dist: testfixtures ; extra == 'test'
